pyramid_ldap/__init__.py
pyramid_ldap/tests.py
pyramid_ldap-0.3.1.post1.dist-info/LICENSE.txt
pyramid_ldap-0.3.1.post1.dist-info/METADATA
pyramid_ldap-0.3.1.post1.dist-info/RECORD
pyramid_ldap-0.3.1.post1.dist-info/WHEEL
pyramid_ldap-0.3.1.post1.dist-info/entry_points.txt
pyramid_ldap-0.3.1.post1.dist-info/top_level.txt
sampleapp/__init__.py
sampleapp/views.py
sampleapp/templates/login.pt
