Metadata-Version: 2.1
Name: pyramid-ldap
Version: 0.3.1.post1
Summary: pyramid_ldap
Home-page: https://pylonsproject.org
Author: Chris McDonough
Author-email: pylons-discuss@groups.google.com
License: BSD-derived (http://www.repoze.org/LICENSE.txt)
Keywords: web pyramid pylons ldap
Platform: UNKNOWN
Classifier: Programming Language :: Python
Classifier: Framework :: Pylons
Classifier: Programming Language :: Python :: 2.7
Classifier: Programming Language :: Python :: 3.6
Classifier: Programming Language :: Python :: 3.7
Classifier: Topic :: System :: Systems Administration :: Authentication/Directory :: LDAP
Classifier: License :: Repoze Public License
Provides-Extra: docs
Provides-Extra: testing
Provides-Extra: sampleapp
Requires-Dist: pyramid (>=1.3)
Requires-Dist: six
Requires-Dist: ldappool (>=2.2.0)
Requires-Dist: python-ldap (>=3.0)
Provides-Extra: docs
Requires-Dist: Sphinx (>=1.7.4); extra == 'docs'
Requires-Dist: pylons-sphinx-themes; extra == 'docs'
Provides-Extra: sampleapp
Requires-Dist: waitress; extra == 'sampleapp'
Requires-Dist: pyramid-debugtoolbar; extra == 'sampleapp'
Provides-Extra: testing
Requires-Dist: nose; extra == 'testing'
Requires-Dist: coverage; extra == 'testing'
